{
  "address": "BHTRWbEGRfJZSVXkJXj1Cv48knuALpUvijJwvuobyvvB",
  "metadata": {
    "name": "vault_mvp",
    "version": "0.1.0",
    "spec": "0.1.0",
    "description": "Created with Anchor"
  },
  "instructions": [
    {
      "name": "collect_weekly_management_fees",
      "docs": [
        "Collect accrued management fees from vault USDC and distribute 70/30"
      ],
      "discriminator": [
        20,
        115,
        148,
        149,
        165,
        31,
        203,
        67
      ],
      "accounts": [
        {
          "name": "collector",
          "docs": [
            "Any signer triggering collection (keeper/admin)"
          ],
          "writable": true,
          "signer": true
        },
        {
          "name": "factory",
          "docs": [
            "Factory PDA - seeds: [\"factory_v2\"]"
          ],
          "pda": {
            "seeds": [
              {
                "kind": "const",
                "value": [
                  102,
                  97,
                  99,
                  116,
                  111,
                  114,
                  121,
                  95,
                  118,
                  50
                ]
              }
            ]
          }
        },
        {
          "name": "vault",
          "docs": [
            "Vault PDA - seeds: [\"vault\", factory.key(), vault_index]"
          ],
          "writable": true,
          "pda": {
            "seeds": [
              {
                "kind": "const",
                "value": [
                  118,
                  97,
                  117,
                  108,
                  116
                ]
              },
              {
                "kind": "account",
                "path": "factory"
              },
              {
                "kind": "arg",
                "path": "vault_index"
              }
            ]
          }
        },
        {
          "name": "vault_stablecoin_account",
          "docs": [
            "Vault's USDC account to pay fees from"
          ],
          "writable": true,
          "pda": {
            "seeds": [
              {
                "kind": "const",
                "value": [
                  118,
                  97,
                  117,
                  108,
                  116,
                  95,
                  115,
                  116,
                  97,
                  98,
                  108,
                  101,
                  99,
                  111,
                  105,
                  110,
                  95,
                  97,
                  99,
                  99,
                  111,
                  117,
                  110,
                  116
                ]
              },
              {
                "kind": "account",
                "path": "vault"
              }
            ]
          }
        },
        {
          "name": "vault_admin_stablecoin_account",
          "docs": [
            "Vault admin USDC account (70%)"
          ],
          "writable": true
        },
        {
          "name": "fee_recipient_stablecoin_account",
          "docs": [
            "Protocol fee recipient USDC account (30%)"
          ],
          "writable": true
        },
        {
          "name": "token_program",
          "address": "TokenkegQfeZyiNwAJbNbGKPFXCWuBvf9Ss623VQ5DA"
        },
        {
          "name": "system_program",
          "address": "11111111111111111111111111111111"
        }
      ],
      "args": [
        {
          "name": "vault_index",
          "type": "u32"
        }
      ]
    },
    {
      "name": "create_vault",
      "docs": [
        "Create a new vault with underlying assets and management fees"
      ],
      "discriminator": [
        29,
        237,
        247,
        208,
        193,
        82,
        54,
        135
      ],
      "accounts": [
        {
          "name": "admin",
          "docs": [
            "Admin who creates the vault"
          ],
          "writable": true,
          "signer": true
        },
        {
          "name": "factory",
          "docs": [
            "Factory PDA - seeds: [\"factory_v2\"]"
          ],
          "writable": true,
          "pda": {
            "seeds": [
              {
                "kind": "const",
                "value": [
                  102,
                  97,
                  99,
                  116,
                  111,
                  114,
                  121,
                  95,
                  118,
                  50
                ]
              }
            ]
          }
        },
        {
          "name": "vault",
          "docs": [
            "Vault PDA - seeds: [\"vault\", factory.key(), vault_index]"
          ],
          "writable": true,
          "pda": {
            "seeds": [
              {
                "kind": "const",
                "value": [
                  118,
                  97,
                  117,
                  108,
                  116
                ]
              },
              {
                "kind": "account",
                "path": "factory"
              },
              {
                "kind": "account",
                "path": "factory.vault_count",
                "account": "Factory"
              }
            ]
          }
        },
        {
          "name": "vault_mint",
          "docs": [
            "Vault token mint (SPL token)"
          ],
          "writable": true,
          "pda": {
            "seeds": [
              {
                "kind": "const",
                "value": [
                  118,
                  97,
                  117,
                  108,
                  116,
                  95,
                  109,
                  105,
                  110,
                  116
                ]
              },
              {
                "kind": "account",
                "path": "vault"
              }
            ]
          }
        },
        {
          "name": "vault_token_account",
          "docs": [
            "Vault token account for holding vault tokens"
          ],
          "writable": true,
          "pda": {
            "seeds": [
              {
                "kind": "const",
                "value": [
                  118,
                  97,
                  117,
                  108,
                  116,
                  95,
                  116,
                  111,
                  107,
                  101,
                  110,
                  95,
                  97,
                  99,
                  99,
                  111,
                  117,
                  110,
                  116
                ]
              },
              {
                "kind": "account",
                "path": "vault"
              }
            ]
          }
        },
        {
          "name": "stablecoin_mint",
          "docs": [
            "Stablecoin mint used to pay creation fee (e.g. USDC)"
          ]
        },
        {
          "name": "admin_stablecoin_account",
          "docs": [
            "Admin's stablecoin token account (payer of creation fee)"
          ],
          "writable": true
        },
        {
          "name": "factory_admin_stablecoin_account",
          "docs": [
            "Factory admin's stablecoin token account (recipient of creation fee)"
          ],
          "writable": true
        },
        {
          "name": "token_program",
          "address": "TokenkegQfeZyiNwAJbNbGKPFXCWuBvf9Ss623VQ5DA"
        },
        {
          "name": "system_program",
          "address": "11111111111111111111111111111111"
        },
        {
          "name": "rent",
          "address": "SysvarRent111111111111111111111111111111111"
        }
      ],
      "args": [
        {
          "name": "vault_name",
          "type": "string"
        },
        {
          "name": "vault_symbol",
          "type": "string"
        },
        {
          "name": "underlying_assets",
          "type": {
            "vec": {
              "defined": {
                "name": "UnderlyingAsset"
              }
            }
          }
        },
        {
          "name": "management_fees",
          "type": "u16"
        }
      ]
    },
    {
      "name": "deposit",
      "docs": [
        "Deposit any stablecoin into the vault and receive vault tokens"
      ],
      "discriminator": [
        242,
        35,
        198,
        137,
        82,
        225,
        242,
        182
      ],
      "accounts": [
        {
          "name": "user",
          "docs": [
            "User making the deposit"
          ],
          "writable": true,
          "signer": true
        },
        {
          "name": "factory",
          "docs": [
            "Factory PDA - seeds: [\"factory_v2\"]"
          ],
          "pda": {
            "seeds": [
              {
                "kind": "const",
                "value": [
                  102,
                  97,
                  99,
                  116,
                  111,
                  114,
                  121,
                  95,
                  118,
                  50
                ]
              }
            ]
          }
        },
        {
          "name": "vault",
          "docs": [
            "Vault PDA - seeds: [\"vault\", factory.key(), vault_index]"
          ],
          "writable": true,
          "pda": {
            "seeds": [
              {
                "kind": "const",
                "value": [
                  118,
                  97,
                  117,
                  108,
                  116
                ]
              },
              {
                "kind": "account",
                "path": "factory"
              },
              {
                "kind": "arg",
                "path": "vault_index"
              }
            ]
          }
        },
        {
          "name": "vault_mint",
          "docs": [
            "Vault token mint"
          ],
          "writable": true,
          "pda": {
            "seeds": [
              {
                "kind": "const",
                "value": [
                  118,
                  97,
                  117,
                  108,
                  116,
                  95,
                  109,
                  105,
                  110,
                  116
                ]
              },
              {
                "kind": "account",
                "path": "vault"
              }
            ]
          }
        },
        {
          "name": "user_stablecoin_account",
          "docs": [
            "User's stablecoin token account (any stablecoin like USDC, USDT, etc.)"
          ],
          "writable": true
        },
        {
          "name": "stablecoin_mint",
          "docs": [
            "Stablecoin mint (USDC, USDT, etc.)"
          ]
        },
        {
          "name": "vault_stablecoin_account",
          "docs": [
            "Vault's stablecoin token account (to receive deposits)"
          ],
          "writable": true,
          "pda": {
            "seeds": [
              {
                "kind": "const",
                "value": [
                  118,
                  97,
                  117,
                  108,
                  116,
                  95,
                  115,
                  116,
                  97,
                  98,
                  108,
                  101,
                  99,
                  111,
                  105,
                  110,
                  95,
                  97,
                  99,
                  99,
                  111,
                  117,
                  110,
                  116
                ]
              },
              {
                "kind": "account",
                "path": "vault"
              }
            ]
          }
        },
        {
          "name": "user_vault_account",
          "docs": [
            "User's vault token account (to receive vault tokens)"
          ],
          "writable": true
        },
        {
          "name": "fee_recipient_stablecoin_account",
          "docs": [
            "Fee recipient's stablecoin token account"
          ],
          "writable": true
        },
        {
          "name": "vault_admin_stablecoin_account",
          "docs": [
            "Vault admin's stablecoin token account (to receive management fees)"
          ],
          "writable": true
        },
        {
          "name": "jupiter_program",
          "docs": [
            "Jupiter program account (optional - only needed if Jupiter swap is provided)"
          ],
          "writable": true
        },
        {
          "name": "token_program",
          "address": "TokenkegQfeZyiNwAJbNbGKPFXCWuBvf9Ss623VQ5DA"
        },
        {
          "name": "system_program",
          "address": "11111111111111111111111111111111"
        }
      ],
      "args": [
        {
          "name": "vault_index",
          "type": "u32"
        },
        {
          "name": "amount",
          "type": "u64"
        },
        {
          "name": "etf_share_price",
          "type": "u64"
        }
      ]
    },
    {
      "name": "distribute_accrued_fees",
      "docs": [
        "Distribute accrued management fees as vault tokens to vault creator and platform",
        "This aligns fee recipients with vault performance by giving them vault shares"
      ],
      "discriminator": [
        205,
        241,
        193,
        87,
        26,
        33,
        131,
        94
      ],
      "accounts": [
        {
          "name": "collector",
          "docs": [
            "Any signer triggering distribution (keeper/admin)"
          ],
          "writable": true,
          "signer": true
        },
        {
          "name": "factory",
          "docs": [
            "Factory PDA - seeds: [\"factory_v2\"]"
          ],
          "pda": {
            "seeds": [
              {
                "kind": "const",
                "value": [
                  102,
                  97,
                  99,
                  116,
                  111,
                  114,
                  121,
                  95,
                  118,
                  50
                ]
              }
            ]
          }
        },
        {
          "name": "vault",
          "docs": [
            "Vault PDA - seeds: [\"vault\", factory.key(), vault_index]"
          ],
          "writable": true,
          "pda": {
            "seeds": [
              {
                "kind": "const",
                "value": [
                  118,
                  97,
                  117,
                  108,
                  116
                ]
              },
              {
                "kind": "account",
                "path": "factory"
              },
              {
                "kind": "arg",
                "path": "vault_index"
              }
            ]
          }
        },
        {
          "name": "vault_mint",
          "docs": [
            "Vault token mint (for minting fee shares)"
          ],
          "writable": true,
          "pda": {
            "seeds": [
              {
                "kind": "const",
                "value": [
                  118,
                  97,
                  117,
                  108,
                  116,
                  95,
                  109,
                  105,
                  110,
                  116
                ]
              },
              {
                "kind": "account",
                "path": "vault"
              }
            ]
          }
        },
        {
          "name": "vault_admin_vault_account",
          "docs": [
            "Vault admin's vault token account (receives vault creator share)"
          ],
          "writable": true
        },
        {
          "name": "fee_recipient_vault_account",
          "docs": [
            "Platform fee recipient's vault token account (receives platform share)"
          ],
          "writable": true
        },
        {
          "name": "token_program",
          "address": "TokenkegQfeZyiNwAJbNbGKPFXCWuBvf9Ss623VQ5DA"
        },
        {
          "name": "system_program",
          "address": "11111111111111111111111111111111"
        }
      ],
      "args": [
        {
          "name": "vault_index",
          "type": "u32"
        }
      ]
    },
    {
      "name": "execute_swaps",
      "docs": [
        "Execute Jupiter swaps for vault's USDC into underlying assets"
      ],
      "discriminator": [
        131,
        242,
        180,
        205,
        235,
        179,
        105,
        117
      ],
      "accounts": [
        {
          "name": "executor",
          "docs": [
            "Vault admin or authorized user executing swaps"
          ],
          "writable": true,
          "signer": true
        },
        {
          "name": "factory",
          "docs": [
            "Factory PDA - seeds: [\"factory_v2\"]"
          ],
          "pda": {
            "seeds": [
              {
                "kind": "const",
                "value": [
                  102,
                  97,
                  99,
                  116,
                  111,
                  114,
                  121,
                  95,
                  118,
                  50
                ]
              }
            ]
          }
        },
        {
          "name": "vault",
          "docs": [
            "Vault PDA - seeds: [\"vault\", factory.key(), vault_index]"
          ],
          "writable": true,
          "pda": {
            "seeds": [
              {
                "kind": "const",
                "value": [
                  118,
                  97,
                  117,
                  108,
                  116
                ]
              },
              {
                "kind": "account",
                "path": "factory"
              },
              {
                "kind": "arg",
                "path": "vault_index"
              }
            ]
          }
        },
        {
          "name": "vault_stablecoin_account",
          "docs": [
            "Vault's stablecoin token account (source of USDC for swaps)"
          ],
          "writable": true,
          "pda": {
            "seeds": [
              {
                "kind": "const",
                "value": [
                  118,
                  97,
                  117,
                  108,
                  116,
                  95,
                  115,
                  116,
                  97,
                  98,
                  108,
                  101,
                  99,
                  111,
                  105,
                  110,
                  95,
                  97,
                  99,
                  99,
                  111,
                  117,
                  110,
                  116
                ]
              },
              {
                "kind": "account",
                "path": "vault"
              }
            ]
          }
        },
        {
          "name": "jupiter_program",
          "docs": [
            "Jupiter program account"
          ]
        },
        {
          "name": "token_program",
          "address": "TokenkegQfeZyiNwAJbNbGKPFXCWuBvf9Ss623VQ5DA"
        },
        {
          "name": "system_program",
          "address": "11111111111111111111111111111111"
        }
      ],
      "args": [
        {
          "name": "vault_index",
          "type": "u32"
        }
      ]
    },
    {
      "name": "finalize_redeem",
      "docs": [
        "Finalize redeem: burn tokens and settle fees/net USDC"
      ],
      "discriminator": [
        6,
        175,
        20,
        155,
        71,
        161,
        109,
        190
      ],
      "accounts": [
        {
          "name": "user",
          "docs": [
            "User redeeming"
          ],
          "writable": true,
          "signer": true
        },
        {
          "name": "factory",
          "docs": [
            "Factory PDA - seeds: [\"factory_v2\"]"
          ],
          "pda": {
            "seeds": [
              {
                "kind": "const",
                "value": [
                  102,
                  97,
                  99,
                  116,
                  111,
                  114,
                  121,
                  95,
                  118,
                  50
                ]
              }
            ]
          }
        },
        {
          "name": "vault",
          "docs": [
            "Vault PDA - seeds: [\"vault\", factory.key(), vault_index]"
          ],
          "writable": true,
          "pda": {
            "seeds": [
              {
                "kind": "const",
                "value": [
                  118,
                  97,
                  117,
                  108,
                  116
                ]
              },
              {
                "kind": "account",
                "path": "factory"
              },
              {
                "kind": "arg",
                "path": "vault_index"
              }
            ]
          }
        },
        {
          "name": "vault_mint",
          "docs": [
            "Vault mint PDA"
          ],
          "writable": true,
          "pda": {
            "seeds": [
              {
                "kind": "const",
                "value": [
                  118,
                  97,
                  117,
                  108,
                  116,
                  95,
                  109,
                  105,
                  110,
                  116
                ]
              },
              {
                "kind": "account",
                "path": "vault"
              }
            ]
          }
        },
        {
          "name": "user_vault_account",
          "docs": [
            "User's vault token account (to burn from)"
          ],
          "writable": true
        },
        {
          "name": "vault_stablecoin_account",
          "docs": [
            "Vault USDC PDA account (source of USDC, filled by client swaps)"
          ],
          "writable": true,
          "pda": {
            "seeds": [
              {
                "kind": "const",
                "value": [
                  118,
                  97,
                  117,
                  108,
                  116,
                  95,
                  115,
                  116,
                  97,
                  98,
                  108,
                  101,
                  99,
                  111,
                  105,
                  110,
                  95,
                  97,
                  99,
                  99,
                  111,
                  117,
                  110,
                  116
                ]
              },
              {
                "kind": "account",
                "path": "vault"
              }
            ]
          }
        },
        {
          "name": "user_stablecoin_account",
          "docs": [
            "User's USDC account (net proceeds destination)"
          ],
          "writable": true
        },
        {
          "name": "fee_recipient_stablecoin_account",
          "docs": [
            "Fee recipient USDC account (factory)"
          ],
          "writable": true
        },
        {
          "name": "vault_admin_stablecoin_account",
          "docs": [
            "Vault admin USDC account (management fee share)"
          ],
          "writable": true
        },
        {
          "name": "token_program",
          "address": "TokenkegQfeZyiNwAJbNbGKPFXCWuBvf9Ss623VQ5DA"
        },
        {
          "name": "system_program",
          "address": "11111111111111111111111111111111"
        }
      ],
      "args": [
        {
          "name": "vault_index",
          "type": "u32"
        },
        {
          "name": "vault_token_amount",
          "type": "u64"
        },
        {
          "name": "etf_share_price",
          "type": "u64"
        }
      ]
    },
    {
      "name": "get_accrued_management_fees",
      "docs": [
        "Get and update accrued management fees for a vault",
        "This function calculates newly accrued fees using live asset prices and balances"
      ],
      "discriminator": [
        134,
        145,
        47,
        94,
        255,
        206,
        143,
        195
      ],
      "accounts": [
        {
          "name": "factory",
          "docs": [
            "Factory PDA - seeds: [\"factory_v2\"]"
          ],
          "pda": {
            "seeds": [
              {
                "kind": "const",
                "value": [
                  102,
                  97,
                  99,
                  116,
                  111,
                  114,
                  121,
                  95,
                  118,
                  50
                ]
              }
            ]
          }
        },
        {
          "name": "vault",
          "docs": [
            "Vault PDA - seeds: [\"vault\", factory.key(), vault_index]"
          ],
          "writable": true,
          "pda": {
            "seeds": [
              {
                "kind": "const",
                "value": [
                  118,
                  97,
                  117,
                  108,
                  116
                ]
              },
              {
                "kind": "account",
                "path": "factory"
              },
              {
                "kind": "arg",
                "path": "vault_index"
              }
            ]
          }
        },
        {
          "name": "vault_stablecoin_account",
          "docs": [
            "Vault's stablecoin token account (USDC/USDT)"
          ],
          "pda": {
            "seeds": [
              {
                "kind": "const",
                "value": [
                  118,
                  97,
                  117,
                  108,
                  116,
                  95,
                  115,
                  116,
                  97,
                  98,
                  108,
                  101,
                  99,
                  111,
                  105,
                  110,
                  95,
                  97,
                  99,
                  99,
                  111,
                  117,
                  110,
                  116
                ]
              },
              {
                "kind": "account",
                "path": "vault"
              }
            ]
          }
        }
      ],
      "args": [
        {
          "name": "vault_index",
          "type": "u32"
        },
        {
          "name": "asset_prices",
          "type": {
            "vec": {
              "defined": {
                "name": "AssetPrice"
              }
            }
          }
        }
      ],
      "returns": {
        "defined": {
          "name": "AccruedManagementFees"
        }
      }
    },
    {
      "name": "get_deposit_details",
      "docs": [
        "Get deposit details for a user and vault"
      ],
      "discriminator": [
        228,
        194,
        58,
        59,
        42,
        195,
        86,
        154
      ],
      "accounts": [
        {
          "name": "user",
          "docs": [
            "User to get deposit details for"
          ],
          "signer": true
        },
        {
          "name": "factory",
          "docs": [
            "Factory PDA - seeds: [\"factory_v2\"]"
          ],
          "pda": {
            "seeds": [
              {
                "kind": "const",
                "value": [
                  102,
                  97,
                  99,
                  116,
                  111,
                  114,
                  121,
                  95,
                  118,
                  50
                ]
              }
            ]
          }
        },
        {
          "name": "vault",
          "docs": [
            "Vault PDA - seeds: [\"vault\", factory.key(), vault_index]"
          ],
          "pda": {
            "seeds": [
              {
                "kind": "const",
                "value": [
                  118,
                  97,
                  117,
                  108,
                  116
                ]
              },
              {
                "kind": "account",
                "path": "factory"
              },
              {
                "kind": "arg",
                "path": "vault_index"
              }
            ]
          }
        },
        {
          "name": "user_vault_account",
          "docs": [
            "User's vault token account"
          ]
        },
        {
          "name": "vault_stablecoin_account",
          "docs": [
            "Vault's stablecoin token account"
          ],
          "pda": {
            "seeds": [
              {
                "kind": "const",
                "value": [
                  118,
                  97,
                  117,
                  108,
                  116,
                  95,
                  115,
                  116,
                  97,
                  98,
                  108,
                  101,
                  99,
                  111,
                  105,
                  110,
                  95,
                  97,
                  99,
                  99,
                  111,
                  117,
                  110,
                  116
                ]
              },
              {
                "kind": "account",
                "path": "vault"
              }
            ]
          }
        }
      ],
      "args": [
        {
          "name": "vault_index",
          "type": "u32"
        }
      ],
      "returns": {
        "defined": {
          "name": "DepositDetails"
        }
      }
    },
    {
      "name": "get_factory_info",
      "docs": [
        "Get factory information including vault count"
      ],
      "discriminator": [
        197,
        39,
        92,
        119,
        18,
        147,
        241,
        190
      ],
      "accounts": [
        {
          "name": "factory",
          "docs": [
            "Factory PDA - seeds: [\"factory_v2\"]"
          ],
          "pda": {
            "seeds": [
              {
                "kind": "const",
                "value": [
                  102,
                  97,
                  99,
                  116,
                  111,
                  114,
                  121,
                  95,
                  118,
                  50
                ]
              }
            ]
          }
        }
      ],
      "args": [],
      "returns": {
        "defined": {
          "name": "FactoryInfo"
        }
      }
    },
    {
      "name": "get_vault_fees",
      "docs": [
        "Get vault fees (factory fees + vault management fees)"
      ],
      "discriminator": [
        207,
        90,
        1,
        204,
        61,
        133,
        107,
        227
      ],
      "accounts": [
        {
          "name": "factory",
          "docs": [
            "Factory PDA - seeds: [\"factory_v2\"]"
          ],
          "pda": {
            "seeds": [
              {
                "kind": "const",
                "value": [
                  102,
                  97,
                  99,
                  116,
                  111,
                  114,
                  121,
                  95,
                  118,
                  50
                ]
              }
            ]
          }
        },
        {
          "name": "vault",
          "docs": [
            "Vault PDA - seeds: [\"vault\", factory.key(), vault_index]"
          ],
          "pda": {
            "seeds": [
              {
                "kind": "const",
                "value": [
                  118,
                  97,
                  117,
                  108,
                  116
                ]
              },
              {
                "kind": "account",
                "path": "factory"
              },
              {
                "kind": "arg",
                "path": "vault_index"
              }
            ]
          }
        }
      ],
      "args": [
        {
          "name": "vault_index",
          "type": "u32"
        }
      ],
      "returns": {
        "defined": {
          "name": "VaultFees"
        }
      }
    },
    {
      "name": "initialize_factory",
      "docs": [
        "Initialize the Factory PDA with fee params and admin"
      ],
      "discriminator": [
        179,
        64,
        75,
        250,
        39,
        254,
        240,
        178
      ],
      "accounts": [
        {
          "name": "admin",
          "docs": [
            "Admin who pays rent and becomes the factory admin"
          ],
          "writable": true,
          "signer": true
        },
        {
          "name": "factory",
          "docs": [
            "Factory PDA - seeds: [\"factory_v2\"]"
          ],
          "writable": true,
          "pda": {
            "seeds": [
              {
                "kind": "const",
                "value": [
                  102,
                  97,
                  99,
                  116,
                  111,
                  114,
                  121,
                  95,
                  118,
                  50
                ]
              }
            ]
          }
        },
        {
          "name": "fee_recipient",
          "docs": [
            "Fee recipient pubkey"
          ]
        },
        {
          "name": "system_program",
          "address": "11111111111111111111111111111111"
        }
      ],
      "args": [
        {
          "name": "entry_fee_bps",
          "type": "u16"
        },
        {
          "name": "exit_fee_bps",
          "type": "u16"
        },
        {
          "name": "vault_creation_fee_usdc",
          "type": "u64"
        },
        {
          "name": "min_management_fee_bps",
          "type": "u16"
        },
        {
          "name": "max_management_fee_bps",
          "type": "u16"
        },
        {
          "name": "vault_creator_fee_ratio_bps",
          "type": "u16"
        },
        {
          "name": "platform_fee_ratio_bps",
          "type": "u16"
        }
      ]
    },
    {
      "name": "set_vault_paused",
      "docs": [
        "Set vault paused or active (admin only)"
      ],
      "discriminator": [
        239,
        131,
        203,
        69,
        243,
        11,
        234,
        153
      ],
      "accounts": [
        {
          "name": "admin",
          "docs": [
            "Admin updating paused state"
          ],
          "writable": true,
          "signer": true
        },
        {
          "name": "factory",
          "docs": [
            "Factory PDA - seeds: [\"factory_v2\"]"
          ],
          "pda": {
            "seeds": [
              {
                "kind": "const",
                "value": [
                  102,
                  97,
                  99,
                  116,
                  111,
                  114,
                  121,
                  95,
                  118,
                  50
                ]
              }
            ]
          }
        },
        {
          "name": "vault",
          "docs": [
            "Vault PDA - seeds: [\"vault\", factory.key(), vault_index]"
          ],
          "writable": true,
          "pda": {
            "seeds": [
              {
                "kind": "const",
                "value": [
                  118,
                  97,
                  117,
                  108,
                  116
                ]
              },
              {
                "kind": "account",
                "path": "factory"
              },
              {
                "kind": "arg",
                "path": "vault_index"
              }
            ]
          }
        },
        {
          "name": "system_program",
          "address": "11111111111111111111111111111111"
        }
      ],
      "args": [
        {
          "name": "vault_index",
          "type": "u32"
        },
        {
          "name": "paused",
          "type": "bool"
        }
      ]
    },
    {
      "name": "transfer_vault_to_user",
      "docs": [
        "Transfer USDC from vault to user for swapping"
      ],
      "discriminator": [
        21,
        41,
        8,
        255,
        228,
        238,
        37,
        212
      ],
      "accounts": [
        {
          "name": "user",
          "docs": [
            "User receiving the USDC from vault"
          ],
          "writable": true,
          "signer": true
        },
        {
          "name": "factory",
          "docs": [
            "Factory PDA - seeds: [\"factory_v2\"]"
          ],
          "pda": {
            "seeds": [
              {
                "kind": "const",
                "value": [
                  102,
                  97,
                  99,
                  116,
                  111,
                  114,
                  121,
                  95,
                  118,
                  50
                ]
              }
            ]
          }
        },
        {
          "name": "vault",
          "docs": [
            "Vault PDA - seeds: [\"vault\", factory.key(), vault_index]"
          ],
          "writable": true,
          "pda": {
            "seeds": [
              {
                "kind": "const",
                "value": [
                  118,
                  97,
                  117,
                  108,
                  116
                ]
              },
              {
                "kind": "account",
                "path": "factory"
              },
              {
                "kind": "arg",
                "path": "vault_index"
              }
            ]
          }
        },
        {
          "name": "vault_stablecoin_account",
          "docs": [
            "Vault's stablecoin token account (source)"
          ],
          "writable": true,
          "pda": {
            "seeds": [
              {
                "kind": "const",
                "value": [
                  118,
                  97,
                  117,
                  108,
                  116,
                  95,
                  115,
                  116,
                  97,
                  98,
                  108,
                  101,
                  99,
                  111,
                  105,
                  110,
                  95,
                  97,
                  99,
                  99,
                  111,
                  117,
                  110,
                  116
                ]
              },
              {
                "kind": "account",
                "path": "vault"
              }
            ]
          }
        },
        {
          "name": "user_stablecoin_account",
          "docs": [
            "User's stablecoin token account (destination)"
          ],
          "writable": true
        },
        {
          "name": "token_program",
          "address": "TokenkegQfeZyiNwAJbNbGKPFXCWuBvf9Ss623VQ5DA"
        },
        {
          "name": "system_program",
          "address": "11111111111111111111111111111111"
        }
      ],
      "args": [
        {
          "name": "vault_index",
          "type": "u32"
        },
        {
          "name": "amount",
          "type": "u64"
        }
      ]
    },
    {
      "name": "update_factory_admin",
      "docs": [
        "Update the factory admin (only current admin)"
      ],
      "discriminator": [
        184,
        83,
        195,
        10,
        115,
        92,
        160,
        182
      ],
      "accounts": [
        {
          "name": "admin",
          "docs": [
            "Current factory admin"
          ],
          "writable": true,
          "signer": true
        },
        {
          "name": "factory",
          "docs": [
            "Factory PDA - seeds: [\"factory_v2\"]"
          ],
          "writable": true,
          "pda": {
            "seeds": [
              {
                "kind": "const",
                "value": [
                  102,
                  97,
                  99,
                  116,
                  111,
                  114,
                  121,
                  95,
                  118,
                  50
                ]
              }
            ]
          }
        },
        {
          "name": "new_admin",
          "docs": [
            "New admin to set on the factory"
          ]
        }
      ],
      "args": []
    },
    {
      "name": "update_factory_fees",
      "docs": [
        "Update factory fees (only admin can call this)"
      ],
      "discriminator": [
        188,
        151,
        209,
        161,
        52,
        40,
        223,
        205
      ],
      "accounts": [
        {
          "name": "admin",
          "docs": [
            "Admin who can update factory fees"
          ],
          "writable": true,
          "signer": true
        },
        {
          "name": "factory",
          "docs": [
            "Factory PDA - seeds: [\"factory_v2\"]"
          ],
          "writable": true,
          "pda": {
            "seeds": [
              {
                "kind": "const",
                "value": [
                  102,
                  97,
                  99,
                  116,
                  111,
                  114,
                  121,
                  95,
                  118,
                  50
                ]
              }
            ]
          }
        }
      ],
      "args": [
        {
          "name": "entry_fee_bps",
          "type": "u16"
        },
        {
          "name": "exit_fee_bps",
          "type": "u16"
        },
        {
          "name": "vault_creation_fee_usdc",
          "type": "u64"
        },
        {
          "name": "min_management_fee_bps",
          "type": "u16"
        },
        {
          "name": "max_management_fee_bps",
          "type": "u16"
        },
        {
          "name": "vault_creator_fee_ratio_bps",
          "type": "u16"
        },
        {
          "name": "platform_fee_ratio_bps",
          "type": "u16"
        }
      ]
    },
    {
      "name": "withdraw_underlying_to_user",
      "docs": [
        "Withdraw underlying asset from vault to user (for client-side redeem swaps)"
      ],
      "discriminator": [
        146,
        25,
        134,
        247,
        140,
        38,
        144,
        170
      ],
      "accounts": [
        {
          "name": "user",
          "docs": [
            "User redeeming (and receiving the asset)"
          ],
          "writable": true,
          "signer": true
        },
        {
          "name": "factory",
          "docs": [
            "Factory PDA - seeds: [\"factory_v2\"]"
          ],
          "pda": {
            "seeds": [
              {
                "kind": "const",
                "value": [
                  102,
                  97,
                  99,
                  116,
                  111,
                  114,
                  121,
                  95,
                  118,
                  50
                ]
              }
            ]
          }
        },
        {
          "name": "vault",
          "docs": [
            "Vault PDA - seeds: [\"vault\", factory.key(), vault_index]"
          ],
          "writable": true,
          "pda": {
            "seeds": [
              {
                "kind": "const",
                "value": [
                  118,
                  97,
                  117,
                  108,
                  116
                ]
              },
              {
                "kind": "account",
                "path": "factory"
              },
              {
                "kind": "arg",
                "path": "vault_index"
              }
            ]
          }
        },
        {
          "name": "vault_asset_account",
          "docs": [
            "Source: vault's ATA for the asset"
          ],
          "writable": true
        },
        {
          "name": "user_asset_account",
          "docs": [
            "Destination: user's ATA for the asset"
          ],
          "writable": true
        },
        {
          "name": "token_program",
          "address": "TokenkegQfeZyiNwAJbNbGKPFXCWuBvf9Ss623VQ5DA"
        },
        {
          "name": "system_program",
          "address": "11111111111111111111111111111111"
        }
      ],
      "args": [
        {
          "name": "vault_index",
          "type": "u32"
        },
        {
          "name": "amount",
          "type": "u64"
        }
      ]
    }
  ],
  "accounts": [
    {
      "name": "Factory",
      "discriminator": [
        159,
        68,
        192,
        61,
        48,
        249,
        216,
        202
      ]
    },
    {
      "name": "Vault",
      "discriminator": [
        211,
        8,
        232,
        43,
        2,
        152,
        117,
        119
      ]
    }
  ],
  "events": [
    {
      "name": "AccruedFeesDistributed",
      "discriminator": [
        143,
        6,
        161,
        12,
        246,
        45,
        154,
        237
      ]
    },
    {
      "name": "DepositEvent",
      "discriminator": [
        120,
        248,
        61,
        83,
        31,
        142,
        107,
        144
      ]
    },
    {
      "name": "FactoryAdminUpdated",
      "discriminator": [
        166,
        214,
        90,
        195,
        44,
        102,
        200,
        52
      ]
    },
    {
      "name": "FactoryFeesUpdated",
      "discriminator": [
        151,
        136,
        58,
        41,
        189,
        89,
        8,
        240
      ]
    },
    {
      "name": "FactoryInitialized",
      "discriminator": [
        20,
        86,
        103,
        75,
        20,
        220,
        162,
        63
      ]
    },
    {
      "name": "RedeemEvent",
      "discriminator": [
        90,
        114,
        83,
        146,
        212,
        26,
        217,
        59
      ]
    },
    {
      "name": "VaultCreated",
      "discriminator": [
        117,
        25,
        120,
        254,
        75,
        236,
        78,
        115
      ]
    },
    {
      "name": "VaultPaused",
      "discriminator": [
        198,
        157,
        22,
        151,
        68,
        100,
        162,
        35
      ]
    },
    {
      "name": "VaultResumed",
      "discriminator": [
        208,
        173,
        238,
        64,
        33,
        63,
        226,
        151
      ]
    }
  ],
  "errors": [
    {
      "code": 6000,
      "name": "FeesTooHigh",
      "msg": "Fees are too high"
    },
    {
      "code": 6001,
      "name": "InvalidFeeRange",
      "msg": "Invalid fee range (min > max)"
    },
    {
      "code": 6002,
      "name": "VaultNameTooLong",
      "msg": "Vault name is too long"
    },
    {
      "code": 6003,
      "name": "VaultSymbolTooLong",
      "msg": "Vault symbol is too long"
    },
    {
      "code": 6004,
      "name": "InvalidUnderlyingAssets",
      "msg": "Invalid underlying assets configuration"
    },
    {
      "code": 6005,
      "name": "AccountTooLarge",
      "msg": "Account size exceeds maximum allowed"
    },
    {
      "code": 6006,
      "name": "InvalidManagementFees",
      "msg": "Invalid management fees"
    },
    {
      "code": 6007,
      "name": "InvalidBpsSum",
      "msg": "Invalid BPS sum - must equal 10000 (100%)"
    },
    {
      "code": 6008,
      "name": "VaultNotFound",
      "msg": "Vault not found"
    },
    {
      "code": 6009,
      "name": "VaultNotActive",
      "msg": "Vault is not active"
    },
    {
      "code": 6010,
      "name": "InvalidAmount",
      "msg": "Invalid amount"
    },
    {
      "code": 6011,
      "name": "FactoryNotActive",
      "msg": "Factory is not active"
    },
    {
      "code": 6012,
      "name": "Unauthorized",
      "msg": "Unauthorized access"
    },
    {
      "code": 6013,
      "name": "InsufficientVaultTokens",
      "msg": "Insufficient vault tokens"
    },
    {
      "code": 6014,
      "name": "InsufficientFunds",
      "msg": "Insufficient funds"
    }
  ],
  "types": [
    {
      "name": "AccruedFeesDistributed",
      "type": {
        "kind": "struct",
        "fields": [
          {
            "name": "vault",
            "type": "pubkey"
          },
          {
            "name": "collector",
            "type": "pubkey"
          },
          {
            "name": "vault_index",
            "type": "u32"
          },
          {
            "name": "total_accrued_fees_usdc",
            "type": "u64"
          },
          {
            "name": "vault_creator_share_tokens",
            "type": "u64"
          },
          {
            "name": "platform_share_tokens",
            "type": "u64"
          },
          {
            "name": "vault_creator_fee_ratio_bps",
            "type": "u16"
          },
          {
            "name": "platform_fee_ratio_bps",
            "type": "u16"
          },
          {
            "name": "timestamp",
            "type": "i64"
          }
        ]
      }
    },
    {
      "name": "AccruedManagementFees",
      "type": {
        "kind": "struct",
        "fields": [
          {
            "name": "vault_index",
            "type": "u32"
          },
          {
            "name": "vault_name",
            "type": "string"
          },
          {
            "name": "vault_symbol",
            "type": "string"
          },
          {
            "name": "vault_admin",
            "type": "pubkey"
          },
          {
            "name": "management_fee_bps",
            "type": "u16"
          },
          {
            "name": "nav",
            "type": "u64"
          },
          {
            "name": "gav",
            "type": "u64"
          },
          {
            "name": "last_fee_accrual_ts",
            "type": "i64"
          },
          {
            "name": "current_timestamp",
            "type": "i64"
          },
          {
            "name": "elapsed_seconds",
            "type": "i64"
          },
          {
            "name": "previously_accrued_fees",
            "type": "u64"
          },
          {
            "name": "newly_accrued_fees",
            "type": "u64"
          },
          {
            "name": "total_accrued_fees",
            "type": "u64"
          },
          {
            "name": "asset_balances",
            "type": {
              "vec": {
                "defined": {
                  "name": "AssetBalance"
                }
              }
            }
          }
        ]
      }
    },
    {
      "name": "AssetBalance",
      "type": {
        "kind": "struct",
        "fields": [
          {
            "name": "mint_address",
            "type": "pubkey"
          },
          {
            "name": "balance",
            "type": "u64"
          },
          {
            "name": "price_usd",
            "type": "u64"
          },
          {
            "name": "value_usd",
            "type": "u64"
          }
        ]
      }
    },
    {
      "name": "AssetPrice",
      "type": {
        "kind": "struct",
        "fields": [
          {
            "name": "mint_address",
            "type": "pubkey"
          },
          {
            "name": "price_usd",
            "type": "u64"
          }
        ]
      }
    },
    {
      "name": "DepositDetails",
      "type": {
        "kind": "struct",
        "fields": [
          {
            "name": "vault_address",
            "type": "pubkey"
          },
          {
            "name": "vault_index",
            "type": "u32"
          },
          {
            "name": "vault_name",
            "type": "string"
          },
          {
            "name": "vault_symbol",
            "type": "string"
          },
          {
            "name": "user_address",
            "type": "pubkey"
          },
          {
            "name": "user_vault_token_balance",
            "type": "u64"
          },
          {
            "name": "vault_total_assets",
            "type": "u64"
          },
          {
            "name": "vault_total_supply",
            "type": "u64"
          },
          {
            "name": "vault_stablecoin_balance",
            "type": "u64"
          },
          {
            "name": "stablecoin_mint",
            "type": "pubkey"
          },
          {
            "name": "vault_state",
            "type": {
              "defined": {
                "name": "VaultState"
              }
            }
          },
          {
            "name": "created_at",
            "type": "i64"
          }
        ]
      }
    },
    {
      "name": "DepositEvent",
      "type": {
        "kind": "struct",
        "fields": [
          {
            "name": "vault",
            "type": "pubkey"
          },
          {
            "name": "user",
            "type": "pubkey"
          },
          {
            "name": "stablecoin_mint",
            "type": "pubkey"
          },
          {
            "name": "amount",
            "type": "u64"
          },
          {
            "name": "entry_fee",
            "type": "u64"
          },
          {
            "name": "vault_tokens_minted",
            "type": "u64"
          },
          {
            "name": "timestamp",
            "type": "i64"
          }
        ]
      }
    },
    {
      "name": "Factory",
      "type": {
        "kind": "struct",
        "fields": [
          {
            "name": "bump",
            "type": "u8"
          },
          {
            "name": "admin",
            "type": "pubkey"
          },
          {
            "name": "fee_recipient",
            "type": "pubkey"
          },
          {
            "name": "vault_count",
            "type": "u32"
          },
          {
            "name": "state",
            "type": {
              "defined": {
                "name": "FactoryState"
              }
            }
          },
          {
            "name": "entry_fee_bps",
            "type": "u16"
          },
          {
            "name": "exit_fee_bps",
            "type": "u16"
          },
          {
            "name": "vault_creation_fee_usdc",
            "type": "u64"
          },
          {
            "name": "min_management_fee_bps",
            "type": "u16"
          },
          {
            "name": "max_management_fee_bps",
            "type": "u16"
          },
          {
            "name": "vault_creator_fee_ratio_bps",
            "type": "u16"
          },
          {
            "name": "platform_fee_ratio_bps",
            "type": "u16"
          }
        ]
      }
    },
    {
      "name": "FactoryAdminUpdated",
      "type": {
        "kind": "struct",
        "fields": [
          {
            "name": "previous_admin",
            "type": "pubkey"
          },
          {
            "name": "new_admin",
            "type": "pubkey"
          },
          {
            "name": "timestamp",
            "type": "i64"
          }
        ]
      }
    },
    {
      "name": "FactoryFeesUpdated",
      "type": {
        "kind": "struct",
        "fields": [
          {
            "name": "admin",
            "type": "pubkey"
          },
          {
            "name": "entry_fee_bps",
            "type": "u16"
          },
          {
            "name": "exit_fee_bps",
            "type": "u16"
          },
          {
            "name": "vault_creation_fee_usdc",
            "type": "u64"
          },
          {
            "name": "min_management_fee_bps",
            "type": "u16"
          },
          {
            "name": "max_management_fee_bps",
            "type": "u16"
          },
          {
            "name": "vault_creator_fee_ratio_bps",
            "type": "u16"
          },
          {
            "name": "platform_fee_ratio_bps",
            "type": "u16"
          },
          {
            "name": "timestamp",
            "type": "i64"
          }
        ]
      }
    },
    {
      "name": "FactoryInfo",
      "type": {
        "kind": "struct",
        "fields": [
          {
            "name": "factory_address",
            "type": "pubkey"
          },
          {
            "name": "admin",
            "type": "pubkey"
          },
          {
            "name": "fee_recipient",
            "type": "pubkey"
          },
          {
            "name": "vault_count",
            "type": "u32"
          },
          {
            "name": "state",
            "type": {
              "defined": {
                "name": "FactoryState"
              }
            }
          },
          {
            "name": "entry_fee_bps",
            "type": "u16"
          },
          {
            "name": "exit_fee_bps",
            "type": "u16"
          },
          {
            "name": "vault_creation_fee_usdc",
            "type": "u64"
          },
          {
            "name": "min_management_fee_bps",
            "type": "u16"
          },
          {
            "name": "max_management_fee_bps",
            "type": "u16"
          },
          {
            "name": "vault_creator_fee_ratio_bps",
            "type": "u16"
          },
          {
            "name": "platform_fee_ratio_bps",
            "type": "u16"
          }
        ]
      }
    },
    {
      "name": "FactoryInitialized",
      "type": {
        "kind": "struct",
        "fields": [
          {
            "name": "admin",
            "type": "pubkey"
          },
          {
            "name": "fee_recipient",
            "type": "pubkey"
          },
          {
            "name": "entry_fee_bps",
            "type": "u16"
          },
          {
            "name": "exit_fee_bps",
            "type": "u16"
          },
          {
            "name": "vault_creation_fee_usdc",
            "type": "u64"
          },
          {
            "name": "min_management_fee_bps",
            "type": "u16"
          },
          {
            "name": "max_management_fee_bps",
            "type": "u16"
          },
          {
            "name": "vault_creator_fee_ratio_bps",
            "type": "u16"
          },
          {
            "name": "platform_fee_ratio_bps",
            "type": "u16"
          },
          {
            "name": "timestamp",
            "type": "i64"
          }
        ]
      }
    },
    {
      "name": "FactoryState",
      "type": {
        "kind": "enum",
        "variants": [
          {
            "name": "Active"
          },
          {
            "name": "Paused"
          },
          {
            "name": "Deprecated"
          }
        ]
      }
    },
    {
      "name": "RedeemEvent",
      "type": {
        "kind": "struct",
        "fields": [
          {
            "name": "vault",
            "type": "pubkey"
          },
          {
            "name": "user",
            "type": "pubkey"
          },
          {
            "name": "stablecoin_mint",
            "type": "pubkey"
          },
          {
            "name": "vault_tokens_burned",
            "type": "u64"
          },
          {
            "name": "exit_fee",
            "type": "u64"
          },
          {
            "name": "stablecoin_amount_redeemed",
            "type": "u64"
          },
          {
            "name": "timestamp",
            "type": "i64"
          }
        ]
      }
    },
    {
      "name": "UnderlyingAsset",
      "type": {
        "kind": "struct",
        "fields": [
          {
            "name": "mint_address",
            "type": "pubkey"
          },
          {
            "name": "mint_bps",
            "type": "u16"
          }
        ]
      }
    },
    {
      "name": "Vault",
      "type": {
        "kind": "struct",
        "fields": [
          {
            "name": "bump",
            "type": "u8"
          },
          {
            "name": "vault_index",
            "type": "u32"
          },
          {
            "name": "factory",
            "type": "pubkey"
          },
          {
            "name": "admin",
            "type": "pubkey"
          },
          {
            "name": "vault_name",
            "type": "string"
          },
          {
            "name": "vault_symbol",
            "type": "string"
          },
          {
            "name": "underlying_assets",
            "type": {
              "vec": {
                "defined": {
                  "name": "UnderlyingAsset"
                }
              }
            }
          },
          {
            "name": "management_fees",
            "type": "u16"
          },
          {
            "name": "state",
            "type": {
              "defined": {
                "name": "VaultState"
              }
            }
          },
          {
            "name": "total_assets",
            "type": "u64"
          },
          {
            "name": "total_supply",
            "type": "u64"
          },
          {
            "name": "created_at",
            "type": "i64"
          },
          {
            "name": "last_fee_accrual_ts",
            "type": "i64"
          },
          {
            "name": "accrued_management_fees_usdc",
            "type": "u64"
          }
        ]
      }
    },
    {
      "name": "VaultCreated",
      "type": {
        "kind": "struct",
        "fields": [
          {
            "name": "vault",
            "type": "pubkey"
          },
          {
            "name": "factory",
            "type": "pubkey"
          },
          {
            "name": "admin",
            "type": "pubkey"
          },
          {
            "name": "vault_index",
            "type": "u32"
          },
          {
            "name": "vault_name",
            "type": "string"
          },
          {
            "name": "vault_symbol",
            "type": "string"
          },
          {
            "name": "underlying_assets",
            "type": {
              "vec": {
                "defined": {
                  "name": "UnderlyingAsset"
                }
              }
            }
          },
          {
            "name": "management_fees",
            "type": "u16"
          },
          {
            "name": "timestamp",
            "type": "i64"
          }
        ]
      }
    },
    {
      "name": "VaultFees",
      "type": {
        "kind": "struct",
        "fields": [
          {
            "name": "entry_fee_bps",
            "type": "u16"
          },
          {
            "name": "exit_fee_bps",
            "type": "u16"
          },
          {
            "name": "vault_creation_fee_usdc",
            "type": "u64"
          },
          {
            "name": "min_management_fee_bps",
            "type": "u16"
          },
          {
            "name": "max_management_fee_bps",
            "type": "u16"
          },
          {
            "name": "vault_management_fees",
            "type": "u16"
          },
          {
            "name": "vault_index",
            "type": "u32"
          },
          {
            "name": "vault_name",
            "type": "string"
          },
          {
            "name": "vault_symbol",
            "type": "string"
          },
          {
            "name": "vault_admin",
            "type": "pubkey"
          }
        ]
      }
    },
    {
      "name": "VaultPaused",
      "type": {
        "kind": "struct",
        "fields": [
          {
            "name": "vault",
            "type": "pubkey"
          },
          {
            "name": "admin",
            "type": "pubkey"
          },
          {
            "name": "timestamp",
            "type": "i64"
          }
        ]
      }
    },
    {
      "name": "VaultResumed",
      "type": {
        "kind": "struct",
        "fields": [
          {
            "name": "vault",
            "type": "pubkey"
          },
          {
            "name": "admin",
            "type": "pubkey"
          },
          {
            "name": "timestamp",
            "type": "i64"
          }
        ]
      }
    },
    {
      "name": "VaultState",
      "type": {
        "kind": "enum",
        "variants": [
          {
            "name": "Active"
          },
          {
            "name": "Paused"
          },
          {
            "name": "Closed"
          }
        ]
      }
    }
  ]
}